hellokeson.py
hellokeson-0.1.0.dist-info/LICENSE.txt
hellokeson-0.1.0.dist-info/METADATA
hellokeson-0.1.0.dist-info/WHEEL
hellokeson-0.1.0.dist-info/top_level.txt
hellokeson-0.1.0.dist-info/RECORD
