Metadata-Version: 2.1
Name: hellokeson
Version: 0.1.0
Summary: Hello,Keson.
Home-page: https://github.com/KesonStar/PythonTest
Author: KesonStar
Author-email: 1183213982@qq.com
License: MIT
Classifier: License :: OSI Approved :: MIT License
Classifier: Programming Language :: Python
Classifier: Programming Language :: Python :: 3
Classifier: Programming Language :: Python :: 3.6
Classifier: Programming Language :: Python :: Implementation :: CPython
Classifier: Programming Language :: Python :: Implementation :: PyPy
Requires-Python: >=3.6.0
License-File: LICENSE.txt
